README.md
__version__.py
ftd2xx.dll
ftd2xx64.dll
ftdi_serial.py
setup.py
ftdi_serial.egg-info/PKG-INFO
ftdi_serial.egg-info/SOURCES.txt
ftdi_serial.egg-info/dependency_links.txt
ftdi_serial.egg-info/requires.txt
ftdi_serial.egg-info/top_level.txt