Metadata-Version: 2.1
Name: ftdi-serial
Version: 0.1.12
Summary: A serial library that uses the FTDI driver where possible for more reliable serial communications.
Home-page: https://gitlab.com/ada-chem/ftdi_serial
Author: Sean Clark
Author-email: sesan@v13inc.com
License: MIT
Platform: UNKNOWN
Requires-Python: >=3.6.0
